fenxi/__init__.py
fenxi/cli.py
fenxi-0.1.0.dist-info/LICENSE
fenxi-0.1.0.dist-info/METADATA
fenxi-0.1.0.dist-info/WHEEL
fenxi-0.1.0.dist-info/entry_points.txt
fenxi-0.1.0.dist-info/top_level.txt
fenxi-0.1.0.dist-info/RECORD
